pyfin_sentiment/__init__.py
pyfin_sentiment/model.py
pyfin_sentiment/preprocessing.py
pyfin_sentiment-0.1.1.dist-info/LICENSE
pyfin_sentiment-0.1.1.dist-info/METADATA
pyfin_sentiment-0.1.1.dist-info/WHEEL
pyfin_sentiment-0.1.1.dist-info/top_level.txt
pyfin_sentiment-0.1.1.dist-info/RECORD
