Metadata-Version: 2.1
Name: pyfin-sentiment
Version: 0.1.1
Summary: A library for market sentiment analysis of financial social media posts
Home-page: https://github.com/moritzwilksch/pyfin-sentiment
Author: Moritz Wilksch
Author-email: moritzwilksch@gmail.com
Project-URL: Bug Tracker, https://github.com/moritzwilksch/pyfin-sentiment/issues
Classifier: Programming Language :: Python :: 3
Classifier: License :: OSI Approved :: MIT License
Classifier: Operating System :: OS Independent
Requires-Python: >=3.8
License-File: LICENSE
Requires-Dist: joblib
Requires-Dist: scikit-learn >=1.1.1
Requires-Dist: polars
Requires-Dist: scipy >=1.8.0
